pundass/__init__.py
pundass/pundass.py
pundass-0.1.2.dist-info/METADATA
pundass-0.1.2.dist-info/WHEEL
pundass-0.1.2.dist-info/top_level.txt
pundass-0.1.2.dist-info/RECORD
