Metadata-Version: 2.1
Name: pundass
Version: 0.1.2
Summary: hi
Home-page: UNKNOWN
Author: Semban2690
Author-email: aaro@gmail.com
License: UNKNOWN
Platform: UNKNOWN
Requires-Python: >=2.1
Requires-Dist: requests
